wbtn/__init__.py
wbtn/py.typed
wbtn-0.0.0a2.dist-info/WHEEL
wbtn-0.0.0a2.dist-info/METADATA
wbtn-0.0.0a2.dist-info/RECORD
