Metadata-Version: 2.4
Name: wbtn
Version: 0.0.0a2
Summary: The WBTN open file format
Keywords: webtoon,naver webtoon
Author: ilotoki0804
Author-email: ilotoki0804 <ilotoki0804@gmail.com>
License-Expression: Apache-2.0
Classifier: License :: OSI Approved :: Apache Software License
Classifier: Operating System :: OS Independent
Classifier: Programming Language :: Python :: 3
Classifier: Programming Language :: Python :: 3.11
Classifier: Programming Language :: Python :: 3.12
Classifier: Programming Language :: Python :: 3.13
Requires-Python: >=3.11
Project-URL: Funding, https://www.patreon.com/ilotoki0804
Project-URL: Repository, https://github.com/ilotoki0804/wbtn
